Workbook

Sheet Export Summary
B3: This document was exported from Numbers. Each table was converted to an Excel worksheet. All other objects on each Numbers sheet were placed on separate worksheets. Please be aware that formula calculations may differ in Excel.
B7: Numbers Sheet Name | C7: Numbers Table Name | D7: Excel Worksheet Name
B9: Sheet 1
C10: Table 1 | D10: Sheet 1
B11: Sheet 2
C12: Базовые переменные | D12: Sheet 2 - Базовые переменные
C13: Синие карты | D13: Sheet 2 - Синие карты
C14: Красные карты | D14: Sheet 2 - Красные карты
C15: Вероятность выпадения цвета | D15: Sheet 2 - Вероятность выпадения
C16: Баланс игроков в ход (суммарно) | D16: Sheet 2 - Баланс игроков в ход
C17: Фиолетовые карты | D17: Sheet 2 - Фиолетовые карты
C18: Золотые карты | D18: Sheet 2 - Золотые карты

Sheet Sheet 1
A1: Name | B1: Color | C1: Effect | D1: Cost | E1: Reward | F1: Icon | G1: Description | H1: Weight | I1: Narrative
A2: Кофе-брейк от Искандера | B2: Blue | C2: GETALL 1 | D2: 1 | E2: 1 | F2: Midjourney-1.png | G2: Когда лекция по экономике затянулась, Искандер угощает всех. | H2: 10 | I2: +1 корм всем
A3: Методичка в общий чат | B3: Blue | C3: GETALL 2 | D3: 1 | E3: 2 | F3: Midjourney-2.png | G3: Константин выложил гайд в чат — команда сыта и мотивирована. | H3: 10 | I3: +1 корм всем
A4: Баланс-пати от Константина | B4: Blue | C4: GETALL 3 | D4: 2 | E4: 3 | F4: Midjourney-3.png | G4: После успешной балансировки — мини-праздник. | H4: 10 | I4: +2 корма всем
A5: Синхронизация спринта | B5: Blue | C5: GETALL 4 | D5: 2 | E5: 4 | F5: Midjourney-4.png | G5: Спринт синхронизирован, команда в ресурсе. | H5: 10 | I5: +2 корма всем
A6: Грант на корм для команды | B6: Blue | C6: GETALL 5 | D6: 3 | E6: 5 | F6: Midjourney-5.png | G6: Внешнее финансирование найдено! | H6: 10 | I6: +3 корма всем
A7: Лекция про экономику корма | B7: Blue | C7: GETALL 6 | D7: 3 | E7: 6 | F7: Midjourney-6.png | G7: Искандер объясняет, как корм влияет на метрики. | H7: 10 | I7: +3 корма всем
A8: Дедлайн продлён! | B8: Blue | C8: GETALL 7 | D8: 4 | E8: 7 | F8: Midjourney-7.png | G8: Невероятно! Дедлайн сдвинули. Время на подкрепление. | H8: 10 | I8: +4 корма всем
A9: Командный бонус от Искандера | B9: Blue | C9: GETALL 8 | D9: 4 | E9: 8 | F9: Midjourney-8.png | G9: За успешный этап — бонус от преподавателя. | H9: 10 | I9: +4 корма всем
A10: Защита проекта — всем плюс | B10: Blue | C10: GETALL 9 | D10: 5 | E10: 9 | F10: Midjourney-9.png | G10: Проект защищён на отлично! Преподаватели щедры. | H10: 10 | I10: +5 кормов всем
A11: Финальный релиз: корм для всех | B11: Blue | C11: GETALL 10 | D11: 5 | E11: 10 | F11: Midjourney-10.png | G11: Релиз состоялся! Все получают награду. | H11: 10 | I11: +5 кормов всем
A12: Аудит кормов от Искандера | B12: Red | C12: STEAL_MONEY ALL 1 | D12: 1 | E12: 1 | F12: Flux_cartoon-iskander-with-magnifying-glass-inspecting-ledger_-dr.png | G12: Искандер проверяет бюджет. Найдены излишки — изымаются. | H12: 30 | I12: Заберите 1 корм у всех оппонентов
A13: Проверка ТЗ: штраф за ошибки | B13: Red | C13: STEAL_MONEY ALL 2 | D13: 2 | E13: 2 | F13: Flux_konstantin-with-red-pen-marking-documents_-shadows_-humorous.png | G13: Константин нашёл несоответствия в ТЗ. Штрафуем. | H13: 30 | I13: Заберите 2 корма у всех оппонентов
... A21: Финальная аттестация: корм на кону | B21: Red | C21: STEAL_MONEY ALL 10 | D21: 9 | E21: 10 | F21: Flux_exam-hall-with-red-lighting_-cartoon-professors-at-table_-fo.png | G21: Аттестация решает всё. Победитель забирает ресурсы. | H21: 30 | I21: Заберите 10 кормов у всех оппонентов
A22: Плагиат на митапе | B22: Purple | C22: STEAL_CARD RANDOM | D22: 1 | E22: Карта | F22: Flux_mysterious-silhouette-sneaking-a-card-from-table_-purple-neo.png | G22: Пока все обсуждали архитектуру, вы тихонько взяли чужую идею... | H22: 10 | I22: Украдите случайную карту у случайного соперника
A23: Стипендия за проект | B23: Gold | C23: GET 1 | D23: 3 | E23: 1 | F23: Flux_golden-coin-with-game-controller-icon_-radiant-light_-cartoo.png | G23: Ваш проект заметили! Первая выплата. | H23: 50 | I23: Получите 1 корм из банка
A24: Грант на балансировку | B24: Gold | C24: GET 2 | D24: 7 | E24: 2 | F24: Flux_grant-document-with-golden-seal_-iskander-signing_-cartoon-s.png | G24: Специальный грант на улучшение баланса. | H24: 50 | I24: Получите 2 корма из банка
A25: Инвестиции от Искандера | B25: Gold | C25: GET 3 | D25: 10 | E25: 3 | F25: Flux_iskander-as-angel-investor-with-golden-briefcase_-sparkles_-.png | G25: Искандер верит в ваш проект! Крупные инвестиции. | H25: 50 | I25: Получите 3 корма из банка

Sheet Sheet 2 - Базовые переменные
A1: Базовые переменные
A2: Переменная | B2: Значение
A3: Стартовый баланс, мин. | B3: 3
A4: Стартовый баланс, макс. | B4: 10
A5: Цель победы | B5: 20
A6: Золото за ход | B6: {=(B5-B4)/B9} -> 0.5
A7: Кол-во игроков | B7: 4
A8: Минимальное кол-во раундов | B8: 6
A9: Максимальное кол-во раундов | B9: 20

Sheet Sheet 2 - Синие карты
A1: Синие карты
A2: № | B2: Карта | C2: Цвет | D2: Стоимость | E2: Доход за ход | F2: Средняя прибыль за игру
A3: 1 | C3: Синий | D3: {=F3/'Sheet 2 - Базовые переменные'!$B$7*VLOOKUP(C3,'Sheet 2 - Вероятность выпадения'!$A2:$B6,2,FALSE)} -> 0.52 | E3: 1 | F3: {=AVERAGE('Sheet 2 - Базовые переменные'!$B$8:$B$9)*E3*'Sheet 2 - Базовые переменные'!$B$7*'Sheet 2 - Базовые переменные'!$B$7*VLOOKUP(C3,'Sheet 2 - Вероятность выпадения'!$A2:$B6,2,FALSE)} -> 20.8
A4: 2 | C4: Синий | D4: {=F4/'Sheet 2 - Базовые переменные'!$B$7*VLOOKUP(C4,'Sheet 2 - Вероятность выпадения'!$A2:$B6,2,FALSE)} -> 1.04 | E4: 2 | F4: {=AVERAGE('Sheet 2 - Базовые переменные'!$B$8:$B$9)*E4*'Sheet 2 - Базовые переменные'!$B$7*'Sheet 2 - Базовые переменные'!$B$7*VLOOKUP(C4,'Sheet 2 - Вероятность выпадения'!$A2:$B6,2,FALSE)} -> 41.6
A5: 3 | C5: Синий | D5: {=F5/'Sheet 2 - Базовые переменные'!$B$7*VLOOKUP(C5,'Sheet 2 - Вероятность выпадения'!$A2:$B6,2,FALSE)} -> 1.56 | E5: 3 | F5: {=AVERAGE('Sheet 2 - Базовые переменные'!$B$8:$B$9)*E5*'Sheet 2 - Базовые переменные'!$B$7*'Sheet 2 - Базовые переменные'!$B$7*VLOOKUP(C5,'Sheet 2 - Вероятность выпадения'!$A2:$B6,2,FALSE)} -> 62.4
A6: 4 | C6: Синий | D6: {=F6/'Sheet 2 - Базовые переменные'!$B$7*VLOOKUP(C6,'Sheet 2 - Вероятность выпадения'!$A2:$B6,2,FALSE)} -> 2.08 | E6: 4 | F6: {=AVERAGE('Sheet 2 - Базовые переменные'!$B$8:$B$9)*E6*'Sheet 2 - Базовые переменные'!$B$7*'Sheet 2 - Базовые переменные'!$B$7*VLOOKUP(C6,'Sheet 2 - Вероятность выпадения'!$A2:$B6,2,FALSE)} -> 83.2
A7: 5 | C7: Синий | D7: {=F7/'Sheet 2 - Базовые переменные'!$B$7*VLOOKUP(C7,'Sheet 2 - Вероятность выпадения'!$A2:$B6,2,FALSE)} -> 2.6 | E7: 5 | F7: {=AVERAGE('Sheet 2 - Базовые переменные'!$B$8:$B$9)*E7*'Sheet 2 - Базовые переменные'!$B$7*'Sheet 2 - Базовые переменные'!$B$7*VLOOKUP(C7,'Sheet 2 - Вероятность выпадения'!$A2:$B6,2,FALSE)} -> 104
A8: 6 | C8: Синий | D8: {=F8/'Sheet 2 - Базовые переменные'!$B$7*VLOOKUP(C8,'Sheet 2 - Вероятность выпадения'!$A2:$B6,2,FALSE)} -> 3.12 | E8: 6 | F8: {=AVERAGE('Sheet 2 - Базовые переменные'!$B$8:$B$9)*E8*'Sheet 2 - Базовые переменные'!$B$7*'Sheet 2 - Базовые переменные'!$B$7*VLOOKUP(C8,'Sheet 2 - Вероятность выпадения'!$A2:$B6,2,FALSE)} -> 124.8
A9: 7 | C9: Синий | D9: {=F9/'Sheet 2 - Базовые переменные'!$B$7*VLOOKUP(C9,'Sheet 2 - Вероятность выпадения'!$A2:$B6,2,FALSE)} -> 3.64 | E9: 7 | F9: {=AVERAGE('Sheet 2 - Базовые переменные'!$B$8:$B$9)*E9*'Sheet 2 - Базовые переменные'!$B$7*'Sheet 2 - Базовые переменные'!$B$7*VLOOKUP(C9,'Sheet 2 - Вероятность выпадения'!$A2:$B6,2,FALSE)} -> 145.6
A10: 8 | C10: Синий | D10: {=F10/'Sheet 2 - Базовые переменные'!$B$7*VLOOKUP(C10,'Sheet 2 - Вероятность выпадения'!$A2:$B6,2,FALSE)} -> 4.16 | E10: 8 | F10: {=AVERAGE('Sheet 2 - Базовые переменные'!$B$8:$B$9)*E10*'Sheet 2 - Базовые переменные'!$B$7*'Sheet 2 - Базовые переменные'!$B$7*VLOOKUP(C10,'Sheet 2 - Вероятность выпадения'!$A2:$B6,2,FALSE)} -> 166.4
A11: 9 | C11: Синий | D11: {=F11/'Sheet 2 - Базовые переменные'!$B$7*VLOOKUP(C11,'Sheet 2 - Вероятность выпадения'!$A2:$B6,2,FALSE)} -> 4.68 | E11: 9 | F11: {=AVERAGE('Sheet 2 - Базовые переменные'!$B$8:$B$9)*E11*'Sheet 2 - Базовые переменные'!$B$7*'Sheet 2 - Базовые переменные'!$B$7*VLOOKUP(C11,'Sheet 2 - Вероятность выпадения'!$A2:$B6,2,FALSE)} -> 187.2
A12: 10 | C12: Синий | D12: {=F12/'Sheet 2 - Базовые переменные'!$B$7*VLOOKUP(C12,'Sheet 2 - Вероятность выпадения'!$A2:$B6,2,FALSE)} -> 5.2 | E12: 10 | F12: {=AVERAGE('Sheet 2 - Базовые переменные'!$B$8:$B$9)*E12*'Sheet 2 - Базовые переменные'!$B$7*'Sheet 2 - Базовые переменные'!$B$7*VLOOKUP(C12,'Sheet 2 - Вероятность выпадения'!$A2:$B6,2,FALSE)} -> 208
B13: СРЕДНЯЯ ценность за ход | D13: {=AVERAGE(D3:D12)} -> 2.86 | F13: {=AVERAGE(F3:F12)/AVERAGE('Sheet 2 - Базовые переменные'!B8:B9)} -> 8.8

Sheet Sheet 2 - Красные карты
A1: Красные карты
A2: № | B2: Карта | C2: Цвет | D2: Стоимость | E2: Доход за ход | F2: Средняя прибыль за игру
A3: 1 | C3: Красный | D3: {=F3/'Sheet 2 - Базовые переменные'!$B$7*-1*VLOOKUP(C3,'Sheet 2 - Вероятность выпадения'!$A2:$B6,2,FALSE)} -> 0.8775 | E3: 1 | F3: {=AVERAGE('Sheet 2 - Базовые переменные'!$B$8:$B$9)*E3*(-'Sheet 2 - Базовые переменные'!$B$7+1)*VLOOKUP(C3,'Sheet 2 - Вероятность выпадения'!$A2:$B6,2,FALSE)} -> -11.7
A4: 2 | C4: Красный | D4: {=F4/'Sheet 2 - Базовые переменные'!$B$7*-1*VLOOKUP(C4,'Sheet 2 - Вероятность выпадения'!$A2:$B6,2,FALSE)} -> 1.755 | E4: 2 | F4: {=AVERAGE('Sheet 2 - Базовые переменные'!$B$8:$B$9)*E4*(-'Sheet 2 - Базовые переменные'!$B$7+1)*VLOOKUP(C4,'Sheet 2 - Вероятность выпадения'!$A2:$B6,2,FALSE)} -> -23.4
A5: 3 | C5: Красный | D5: {=F5/'Sheet 2 - Базовые переменные'!$B$7*-1*VLOOKUP(C5,'Sheet 2 - Вероятность выпадения'!$A2:$B6,2,FALSE)} -> 2.6325 | E5: 3 | F5: {=AVERAGE('Sheet 2 - Базовые переменные'!$B$8:$B$9)*E5*(-'Sheet 2 - Базовые переменные'!$B$7+1)*VLOOKUP(C5,'Sheet 2 - Вероятность выпадения'!$A2:$B6,2,FALSE)} -> -35.1
A6: 4 | C6: Красный | D6: {=F6/'Sheet 2 - Базовые переменные'!$B$7*-1*VLOOKUP(C6,'Sheet 2 - Вероятность выпадения'!$A2:$B6,2,FALSE)} -> 3.51 | E6: 4 | F6: {=AVERAGE('Sheet 2 - Базовые переменные'!$B$8:$B$9)*E6*(-'Sheet 2 - Базовые переменные'!$B$7+1)*VLOOKUP(C6,'Sheet 2 - Вероятность выпадения'!$A2:$B6,2,FALSE)} -> -46.8
A7: 5 | C7: Красный | D7: {=F7/'Sheet 2 - Базовые переменные'!$B$7*-1*VLOOKUP(C7,'Sheet 2 - Вероятность выпадения'!$A2:$B6,2,FALSE)} -> 4.3875 | E7: 5 | F7: {=AVERAGE('Sheet 2 - Базовые переменные'!$B$8:$B$9)*E7*(-'Sheet 2 - Базовые переменные'!$B$7+1)*VLOOKUP(C7,'Sheet 2 - Вероятность выпадения'!$A2:$B6,2,FALSE)} -> -58.5
A8: 6 | C8: Красный | D8: {=F8/'Sheet 2 - Базовые переменные'!$B$7*-1*VLOOKUP(C8,'Sheet 2 - Вероятность выпадения'!$A2:$B6,2,FALSE)} -> 5.265 | E8: 6 | F8: {=AVERAGE('Sheet 2 - Базовые переменные'!$B$8:$B$9)*E8*(-'Sheet 2 - Базовые переменные'!$B$7+1)*VLOOKUP(C8,'Sheet 2 - Вероятность выпадения'!$A2:$B6,2,FALSE)} -> -70.2
A9: 7 | C9: Красный | D9: {=F9/'Sheet 2 - Базовые переменные'!$B$7*-1*VLOOKUP(C9,'Sheet 2 - Вероятность выпадения'!$A2:$B6,2,FALSE)} -> 6.1425 | E9: 7 | F9: {=AVERAGE('Sheet 2 - Базовые переменные'!$B$8:$B$9)*E9*(-'Sheet 2 - Базовые переменные'!$B$7+1)*VLOOKUP(C9,'Sheet 2 - Вероятность выпадения'!$A2:$B6,2,FALSE)} -> -81.9
A10: 8 | C10: Красный | D10: {=F10/'Sheet 2 - Базовые переменные'!$B$7*-1*VLOOKUP(C10,'Sheet 2 - Вероятность выпадения'!$A2:$B6,2,FALSE)} -> 7.02 | E10: 8 | F10: {=AVERAGE('Sheet 2 - Базовые переменные'!$B$8:$B$9)*E10*(-'Sheet 2 - Базовые переменные'!$B$7+1)*VLOOKUP(C10,'Sheet 2 - Вероятность выпадения'!$A2:$B6,2,FALSE)} -> -93.6
A11: 9 | C11: Красный | D11: {=F11/'Sheet 2 - Базовые переменные'!$B$7*-1*VLOOKUP(C11,'Sheet 2 - Вероятность выпадения'!$A2:$B6,2,FALSE)} -> 7.8975 | E11: 9 | F11: {=AVERAGE('Sheet 2 - Базовые переменные'!$B$8:$B$9)*E11*(-'Sheet 2 - Базовые переменные'!$B$7+1)*VLOOKUP(C11,'Sheet 2 - Вероятность выпадения'!$A2:$B6,2,FALSE)} -> -105.3
A12: 10 | C12: Красный | D12: {=F12/'Sheet 2 - Базовые переменные'!$B$7*-1*VLOOKUP(C12,'Sheet 2 - Вероятность выпадения'!$A2:$B6,2,FALSE)} -> 8.775 | E12: 10 | F12: {=AVERAGE('Sheet 2 - Базовые переменные'!$B$8:$B$9)*E12*(-'Sheet 2 - Базовые переменные'!$B$7+1)*VLOOKUP(C12,'Sheet 2 - Вероятность выпадения'!$A2:$B6,2,FALSE)} -> -117
B13: СРЕДНЯЯ ценность за ход | D13: {=AVERAGE(D3:D12)} -> 4.82625 | F13: {=AVERAGE(F3:F12)/AVERAGE('Sheet 2 - Базовые переменные'!B8:B9)} -> -4.95

Sheet Sheet 2 - Вероятность выпадения
A1: Вероятность выпадения цвета
A2: Цвет | B2: Вероятность
A3: Синий | B3: 0.1
A4: Красный | B4: 0.3
A5: Фиолетовый | B5: 0.1
A6: Золотой | B6: 0.5

Sheet Sheet 2 - Баланс игроков в ход 
A1: Баланс игроков в ход (суммарно)
C2: Средний доход с карт
A3: Ход | B3: Заработано всегда | C3: {='Sheet 2 - Вероятность выпадения'!$A3} -> Синий | D3: {='Sheet 2 - Вероятность выпадения'!$A4} -> Красный | E3: {='Sheet 2 - Вероятность выпадения'!$A5} -> Фиолетовый | F3: {='Sheet 2 - Вероятность выпадения'!$A6} -> Золотой | G3: Средне заработано | H3: Средне потрачено на игрока | I3: Средне на игрока
A4: 1 | B4: {=(AVERAGE('Sheet 2 - Базовые переменные'!$B$3:$B$4))+$A4*'Sheet 2 - Базовые переменные'!$B$6*'Sheet 2 - Базовые переменные'!$B$7} -> 8.5 | C4: {='Sheet 2 - Синие карты'!$F$13*$A4} -> 8.8 | D4: {='Sheet 2 - Красные карты'!$F$13*$A4} -> -4.95 | E4: {='Sheet 2 - Фиолетовые карты'!$F$4*$A4} -> 0.558 | F4: {='Sheet 2 - Золотые карты'!$F$6*$A4} -> 4 | G4: {=SUM(B4:F4)} -> 16.908 | H4: {=AVERAGE('Sheet 2 - Синие карты'!D$13*'Sheet 2 - Вероятность выпадения'!B$3,'Sheet 2 - Красные карты'!D$13*'Sheet 2 - Вероятность выпадения'!B$4,'Sheet 2 - Фиолетовые карты'!D$4*'Sheet 2 - Вероятность выпадения'!B$5,'Sheet 2 - Золотые карты'!D$6*'Sheet 2 - Вероятность выпадения'!B$6)} -> 1.2505025 | I4: {=G4/'Sheet 2 - Базовые переменные'!$B$7-H4} -> 2.9764975
A5: 2 | B5: {=(AVERAGE('Sheet 2 - Базовые переменные'!$B$3:$B$4))+$A5*'Sheet 2 - Базовые переменные'!$B$6*'Sheet 2 - Базовые переменные'!$B$7} -> 10.5 | C5: {='Sheet 2 - Синие карты'!$F$13*$A5} -> 17.6 | D5: {='Sheet 2 - Красные карты'!$F$13*$A5} -> -9.9 | E5: {='Sheet 2 - Фиолетовые карты'!$F$4*$A5} -> 1.116 | F5: {='Sheet 2 - Золотые карты'!$F$6*$A5} -> 8 | G5: {=SUM(B5:F5)} -> 27.316 | H5: {=AVERAGE('Sheet 2 - Синие карты'!D$13*'Sheet 2 - Вероятность выпадения'!B$3,'Sheet 2 - Красные карты'!D$13*'Sheet 2 - Вероятность выпадения'!B$4,'Sheet 2 - Фиолетовые карты'!D$4*'Sheet 2 - Вероятность выпадения'!B$5,'Sheet 2 - Золотые карты'!D$6*'Sheet 2 - Вероятность выпадения'!B$6)} -> 1.2505025 | I5: {=G5/'Sheet 2 - Базовые переменные'!$B$7-H5} -> 5.5784975
A6: 3 | B6: {=(AVERAGE('Sheet 2 - Базовые переменные'!$B$3:$B$4))+$A6*'Sheet 2 - Базовые переменные'!$B$6*'Sheet 2 - Базовые переменные'!$B$7} -> 12.5 | C6: {='Sheet 2 - Синие карты'!$F$13*$A6} -> 26.4 | D6: {='Sheet 2 - Красные карты'!$F$13*$A6} -> -14.85 | E6: {='Sheet 2 - Фиолетовые карты'!$F$4*$A6} -> 1.674 | F6: {='Sheet 2 - Золотые карты'!$F$6*$A6} -> 12 | G6: {=SUM(B6:F6)} -> 37.724 | H6: {=AVERAGE('Sheet 2 - Синие карты'!D$13*'Sheet 2 - Вероятность выпадения'!B$3,'Sheet 2 - Красные карты'!D$13*'Sheet 2 - Вероятность выпадения'!B$4,'Sheet 2 - Фиолетовые карты'!D$4*'Sheet 2 - Вероятность выпадения'!B$5,'Sheet 2 - Золотые карты'!D$6*'Sheet 2 - Вероятность выпадения'!B$6)} -> 1.2505025 | I6: {=G6/'Sheet 2 - Базовые переменные'!$B$7-H6} -> 8.1804975
A7: 4 | B7: {=(AVERAGE('Sheet 2 - Базовые переменные'!$B$3:$B$4))+$A7*'Sheet 2 - Базовые переменные'!$B$6*'Sheet 2 - Базовые переменные'!$B$7} -> 14.5 | C7: {='Sheet 2 - Синие карты'!$F$13*$A7} -> 35.2 | D7: {='Sheet 2 - Красные карты'!$F$13*$A7} -> -19.8 | E7: {='Sheet 2 - Фиолетовые карты'!$F$4*$A7} -> 2.232 | F7: {='Sheet 2 - Золотые карты'!$F$6*$A7} -> 16 | G7: {=SUM(B7:F7)} -> 48.132 | H7: {=AVERAGE('Sheet 2 - Синие карты'!D$13*'Sheet 2 - Вероятность выпадения'!B$3,'Sheet 2 - Красные карты'!D$13*'Sheet 2 - Вероятность выпадения'!B$4,'Sheet 2 - Фиолетовые карты'!D$4*'Sheet 2 - Вероятность выпадения'!B$5,'Sheet 2 - Золотые карты'!D$6*'Sheet 2 - Вероятность выпадения'!B$6)} -> 1.2505025 | I7: {=G7/'Sheet 2 - Базовые переменные'!$B$7-H7} -> 10.782497
A8: 5 | B8: {=(AVERAGE('Sheet 2 - Базовые переменные'!$B$3:$B$4))+$A8*'Sheet 2 - Базовые переменные'!$B$6*'Sheet 2 - Базовые переменные'!$B$7} -> 16.5 | C8: {='Sheet 2 - Синие карты'!$F$13*$A8} -> 44 | D8: {='Sheet 2 - Красные карты'!$F$13*$A8} -> -24.75 | E8: {='Sheet 2 - Фиолетовые карты'!$F$4*$A8} -> 2.79 | F8: {='Sheet 2 - Золотые карты'!$F$6*$A8} -> 20 | G8: {=SUM(B8:F8)} -> 58.54 | H8: {=AVERAGE('Sheet 2 - Синие карты'!D$13*'Sheet 2 - Вероятность выпадения'!B$3,'Sheet 2 - Красные карты'!D$13*'Sheet 2 - Вероятность выпадения'!B$4,'Sheet 2 - Фиолетовые карты'!D$4*'Sheet 2 - Вероятность выпадения'!B$5,'Sheet 2 - Золотые карты'!D$6*'Sheet 2 - Вероятность выпадения'!B$6)} -> 1.2505025 | I8: {=G8/'Sheet 2 - Базовые переменные'!$B$7-H8} -> 13.384498
A9: 6 | B9: {=(AVERAGE('Sheet 2 - Базовые переменные'!$B$3:$B$4))+$A9*'Sheet 2 - Базовые переменные'!$B$6*'Sheet 2 - Базовые переменные'!$B$7} -> 18.5 | C9: {='Sheet 2 - Синие карты'!$F$13*$A9} -> 52.8 | D9: {='Sheet 2 - Красные карты'!$F$13*$A9} -> -29.7 | E9: {='Sheet 2 - Фиолетовые карты'!$F$4*$A9} -> 3.348 | F9: {='Sheet 2 - Золотые карты'!$F$6*$A9} -> 24 | G9: {=SUM(B9:F9)} -> 68.948 | H9: {=AVERAGE('Sheet 2 - Синие карты'!D$13*'Sheet 2 - Вероятность выпадения'!B$3,'Sheet 2 - Красные карты'!D$13*'Sheet 2 - Вероятность выпадения'!B$4,'Sheet 2 - Фиолетовые карты'!D$4*'Sheet 2 - Вероятность выпадения'!B$5,'Sheet 2 - Золотые карты'!D$6*'Sheet 2 - Вероятность выпадения'!B$6)} -> 1.2505025 | I9: {=G9/'Sheet 2 - Базовые переменные'!$B$7-H9} -> 15.986498
A10: 7 | B10: {=(AVERAGE('Sheet 2 - Базовые переменные'!$B$3:$B$4))+$A10*'Sheet 2 - Базовые переменные'!$B$6*'Sheet 2 - Базовые переменные'!$B$7} -> 20.5 | C10: {='Sheet 2 - Синие карты'!$F$13*$A10} -> 61.6 | D10: {='Sheet 2 - Красные карты'!$F$13*$A10} -> -34.65 | E10: {='Sheet 2 - Фиолетовые карты'!$F$4*$A10} -> 3.906 | F10: {='Sheet 2 - Золотые карты'!$F$6*$A10} -> 28 | G10: {=SUM(B10:F10)} -> 79.356 | H10: {=AVERAGE('Sheet 2 - Синие карты'!D$13*'Sheet 2 - Вероятность выпадения'!B$3,'Sheet 2 - Красные карты'!D$13*'Sheet 2 - Вероятность выпадения'!B$4,'Sheet 2 - Фиолетовые карты'!D$4*'Sheet 2 - Вероятность выпадения'!B$5,'Sheet 2 - Золотые карты'!D$6*'Sheet 2 - Вероятность выпадения'!B$6)} -> 1.2505025 | I10: {=G10/'Sheet 2 - Базовые переменные'!$B$7-H10} -> 18.588497
A11: 8 | B11: {=(AVERAGE('Sheet 2 - Базовые переменные'!$B$3:$B$4))+$A11*'Sheet 2 - Базовые переменные'!$B$6*'Sheet 2 - Базовые переменные'!$B$7} -> 22.5 | C11: {='Sheet 2 - Синие карты'!$F$13*$A11} -> 70.4 | D11: {='Sheet 2 - Красные карты'!$F$13*$A11} -> -39.6 | E11: {='Sheet 2 - Фиолетовые карты'!$F$4*$A11} -> 4.464 | F11: {='Sheet 2 - Золотые карты'!$F$6*$A11} -> 32 | G11: {=SUM(B11:F11)} -> 89.764 | H11: {=AVERAGE('Sheet 2 - Синие карты'!D$13*'Sheet 2 - Вероятность выпадения'!B$3,'Sheet 2 - Красные карты'!D$13*'Sheet 2 - Вероятность выпадения'!B$4,'Sheet 2 - Фиолетовые карты'!D$4*'Sheet 2 - Вероятность выпадения'!B$5,'Sheet 2 - Золотые карты'!D$6*'Sheet 2 - Вероятность выпадения'!B$6)} -> 1.2505025 | I11: {=G11/'Sheet 2 - Базовые переменные'!$B$7-H11} -> 21.190497
A12: 9 | B12: {=(AVERAGE('Sheet 2 - Базовые переменные'!$B$3:$B$4))+$A12*'Sheet 2 - Базовые переменные'!$B$6*'Sheet 2 - Базовые переменные'!$B$7} -> 24.5 | C12: {='Sheet 2 - Синие карты'!$F$13*$A12} -> 79.2 | D12: {='Sheet 2 - Красные карты'!$F$13*$A12} -> -44.55 | E12: {='Sheet 2 - Фиолетовые карты'!$F$4*$A12} -> 5.022 | F12: {='Sheet 2 - Золотые карты'!$F$6*$A12} -> 36 | G12: {=SUM(B12:F12)} -> 100.172 | H12: {=AVERAGE('Sheet 2 - Синие карты'!D$13*'Sheet 2 - Вероятность выпадения'!B$3,'Sheet 2 - Красные карты'!D$13*'Sheet 2 - Вероятность выпадения'!B$4,'Sheet 2 - Фиолетовые карты'!D$4*'Sheet 2 - Вероятность выпадения'!B$5,'Sheet 2 - Золотые карты'!D$6*'Sheet 2 - Вероятность выпадения'!B$6)} -> 1.2505025 | I12: {=G12/'Sheet 2 - Базовые переменные'!$B$7-H12} -> 23.792497
A13: 10 | B13: {=(AVERAGE('Sheet 2 - Базовые переменные'!$B$3:$B$4))+$A13*'Sheet 2 - Базовые переменные'!$B$6*'Sheet 2 - Базовые переменные'!$B$7} -> 26.5 | C13: {='Sheet 2 - Синие карты'!$F$13*$A13} -> 88 | D13: {='Sheet 2 - Красные карты'!$F$13*$A13} -> -49.5 | E13: {='Sheet 2 - Фиолетовые карты'!$F$4*$A13} -> 5.58 | F13: {='Sheet 2 - Золотые карты'!$F$6*$A13} -> 40 | G13: {=SUM(B13:F13)} -> 110.58 | H13: {=AVERAGE('Sheet 2 - Синие карты'!D$13*'Sheet 2 - Вероятность выпадения'!B$3,'Sheet 2 - Красные карты'!D$13*'Sheet 2 - Вероятность выпадения'!B$4,'Sheet 2 - Фиолетовые карты'!D$4*'Sheet 2 - Вероятность выпадения'!B$5,'Sheet 2 - Золотые карты'!D$6*'Sheet 2 - Вероятность выпадения'!B$6)} -> 1.2505025 | I13: {=G13/'Sheet 2 - Базовые переменные'!$B$7-H13} -> 26.394497
A14: 11 | B14: {=(AVERAGE('Sheet 2 - Базовые переменные'!$B$3:$B$4))+$A14*'Sheet 2 - Базовые переменные'!$B$6*'Sheet 2 - Базовые переменные'!$B$7} -> 28.5 | C14: {='Sheet 2 - Синие карты'!$F$13*$A14} -> 96.8 | D14: {='Sheet 2 - Красные карты'!$F$13*$A14} -> -54.45 | E14: {='Sheet 2 - Фиолетовые карты'!$F$4*$A14} -> 6.138 | F14: {='Sheet 2 - Золотые карты'!$F$6*$A14} -> 44 | G14: {=SUM(B14:F14)} -> 120.988 | H14: {=AVERAGE('Sheet 2 - Синие карты'!D$13*'Sheet 2 - Вероятность выпадения'!B$3,'Sheet 2 - Красные карты'!D$13*'Sheet 2 - Вероятность выпадения'!B$4,'Sheet 2 - Фиолетовые карты'!D$4*'Sheet 2 - Вероятность выпадения'!B$5,'Sheet 2 - Золотые карты'!D$6*'Sheet 2 - Вероятность выпадения'!B$6)} -> 1.2505025 | I14: {=G14/'Sheet 2 - Базовые переменные'!$B$7-H14} -> 28.996498
A15: 12 | B15: {=(AVERAGE('Sheet 2 - Базовые переменные'!$B$3:$B$4))+$A15*'Sheet 2 - Базовые переменные'!$B$6*'Sheet 2 - Базовые переменные'!$B$7} -> 30.5 | C15: {='Sheet 2 - Синие карты'!$F$13*$A15} -> 105.6 | D15: {='Sheet 2 - Красные карты'!$F$13*$A15} -> -59.4 | E15: {='Sheet 2 - Фиолетовые карты'!$F$4*$A15} -> 6.696 | F15: {='Sheet 2 - Золотые карты'!$F$6*$A15} -> 48 | G15: {=SUM(B15:F15)} -> 131.396 | H15: {=AVERAGE('Sheet 2 - Синие карты'!D$13*'Sheet 2 - Вероятность выпадения'!B$3,'Sheet 2 - Красные карты'!D$13*'Sheet 2 - Вероятность выпадения'!B$4,'Sheet 2 - Фиолетовые карты'!D$4*'Sheet 2 - Вероятность выпадения'!B$5,'Sheet 2 - Золотые карты'!D$6*'Sheet 2 - Вероятность выпадения'!B$6)} -> 1.2505025 | I15: {=G15/'Sheet 2 - Базовые переменные'!$B$7-H15} -> 31.598498
... A23: 20 | B23: {=(AVERAGE('Sheet 2 - Базовые переменные'!$B$3:$B$4))+$A23*'Sheet 2 - Базовые переменные'!$B$6*'Sheet 2 - Базовые переменные'!$B$7} -> 46.5 | C23: {='Sheet 2 - Синие карты'!$F$13*$A23} -> 176 | D23: {='Sheet 2 - Красные карты'!$F$13*$A23} -> -99 | E23: {='Sheet 2 - Фиолетовые карты'!$F$4*$A23} -> 11.16 | F23: {='Sheet 2 - Золотые карты'!$F$6*$A23} -> 80 | G23: {=SUM(B23:F23)} -> 214.66 | H23: {=AVERAGE('Sheet 2 - Синие карты'!D$13*'Sheet 2 - Вероятность выпадения'!B$3,'Sheet 2 - Красные карты'!D$13*'Sheet 2 - Вероятность выпадения'!B$4,'Sheet 2 - Фиолетовые карты'!D$4*'Sheet 2 - Вероятность выпадения'!B$5,'Sheet 2 - Золотые карты'!D$6*'Sheet 2 - Вероятность выпадения'!B$6)} -> 1.2505025 | I23: {=G23/'Sheet 2 - Базовые переменные'!$B$7-H23} -> 52.414498

Sheet Sheet 2 - Фиолетовые карты
A1: Фиолетовые карты
A2: № | B2: Карта | C2: Цвет | D2: Стоимость | E2: Доход за ход | F2: Средняя прибыль за игру
A3: 1 | C3: Фиолетовый | D3: {=F3/'Sheet 2 - Базовые переменные'!$B$7*VLOOKUP(C3,'Sheet 2 - Вероятность выпадения'!$A2:$B6,2,FALSE)} -> 0.18135 | E3: {='Sheet 2 - Синие карты'!F13*'Sheet 2 - Вероятность выпадения'!B3+'Sheet 2 - Красные карты'!F13*'Sheet 2 - Вероятность выпадения'!B4+'Sheet 2 - Золотые карты'!F6*'Sheet 2 - Вероятность выпадения'!B6} -> 1.395 | F3: {=AVERAGE('Sheet 2 - Базовые переменные'!$B$8:$B$9)*E3*'Sheet 2 - Базовые переменные'!$B$7*VLOOKUP(C3,'Sheet 2 - Вероятность выпадения'!$A2:$B6,2,FALSE)} -> 7.254
B4: СРЕДНЯЯ ценность за ход | D4: {=AVERAGE(D2:D3)} -> 0.18135 | F4: {=AVERAGE(F3:F3)/AVERAGE('Sheet 2 - Базовые переменные'!B8:B9)} -> 0.558

Sheet Sheet 2 - Золотые карты
A1: Золотые карты
A2: № | B2: Карта | C2: Цвет | D2: Стоимость | E2: Доход за ход | F2: Средняя прибыль за игру
A3: 1 | C3: Золотой | D3: {=F3/'Sheet 2 - Базовые переменные'!$B$7*VLOOKUP(C3,'Sheet 2 - Вероятность выпадения'!$A2:$B6,2,FALSE)} -> 3.25 | E3: 1 | F3: {=AVERAGE('Sheet 2 - Базовые переменные'!$B$8:$B$9)*E3*'Sheet 2 - Базовые переменные'!$B$7*VLOOKUP(C3,'Sheet 2 - Вероятность выпадения'!$A2:$B6,2,FALSE)} -> 26
A4: 2 | C4: Золотой | D4: {=F4/'Sheet 2 - Базовые переменные'!$B$7*VLOOKUP(C4,'Sheet 2 - Вероятность выпадения'!$A2:$B6,2,FALSE)} -> 6.5 | E4: 2 | F4: {=AVERAGE('Sheet 2 - Базовые переменные'!$B$8:$B$9)*E4*'Sheet 2 - Базовые переменные'!$B$7*VLOOKUP(C4,'Sheet 2 - Вероятность выпадения'!$A2:$B6,2,FALSE)} -> 52
A5: 3 | C5: Золотой | D5: {=F5/'Sheet 2 - Базовые переменные'!$B$7*VLOOKUP(C5,'Sheet 2 - Вероятность выпадения'!$A2:$B6,2,FALSE)} -> 9.75 | E5: 3 | F5: {=AVERAGE('Sheet 2 - Базовые переменные'!$B$8:$B$9)*E5*'Sheet 2 - Базовые переменные'!$B$7*VLOOKUP(C5,'Sheet 2 - Вероятность выпадения'!$A2:$B6,2,FALSE)} -> 78
B6: СРЕДНЯЯ ценность за ход | D6: {=AVERAGE(D3:D5)} -> 6.5 | F6: {=AVERAGE(F3:F5)/AVERAGE('Sheet 2 - Базовые переменные'!B8:B9)} -> 4
